amochka/__init__.py
amochka/client.py
amochka/errors.py
amochka/etl.py
etl/__init__.py
etl/config.py
etl/extractors.py
etl/loaders.py
etl/run_etl.py
etl/transformers.py
etl/migrations/001_create_tables.sql
amochka-0.4.6.dist-info/METADATA
amochka-0.4.6.dist-info/WHEEL
amochka-0.4.6.dist-info/top_level.txt
amochka-0.4.6.dist-info/RECORD
