Metadata-Version: 2.4
Name: amochka
Version: 0.4.6
Summary: Python library for working with amoCRM API with ETL capabilities
Author-email: Timur <timurdt@gmail.com>
License: MIT
Project-URL: Homepage, https://github.com/yourusername/amochka
Project-URL: Documentation, https://github.com/yourusername/amochka
Project-URL: Repository, https://github.com/yourusername/amochka
Project-URL: Bug Tracker, https://github.com/yourusername/amochka/issues
Keywords: amocrm,crm,api,client,automation,etl
Classifier: Development Status :: 4 - Beta
Classifier: Intended Audience :: Developers
Classifier: License :: OSI Approved :: MIT License
Classifier: Operating System :: OS Independent
Classifier: Programming Language :: Python :: 3
Classifier: Programming Language :: Python :: 3.6
Classifier: Programming Language :: Python :: 3.7
Classifier: Programming Language :: Python :: 3.8
Classifier: Programming Language :: Python :: 3.9
Classifier: Programming Language :: Python :: 3.10
Classifier: Programming Language :: Python :: 3.11
Classifier: Programming Language :: Python :: 3.12
Classifier: Topic :: Software Development :: Libraries :: Python Modules
Classifier: Topic :: Internet :: WWW/HTTP
Requires-Python: >=3.6
Requires-Dist: requests>=2.25.0
Requires-Dist: psycopg2-binary>=2.9.0
Requires-Dist: python-dotenv>=1.0.0
